zipextimporter.py
pexe37/__init__.py
pexe37/__main__.py
pexe37/_wapi.py
pexe37/boot_common.py
pexe37/boot_ctypes_com_server.py
pexe37/boot_service.py
pexe37/build_exe.py
pexe37/distutils_buildexe.py
pexe37/dllfinder.py
pexe37/hooks.py
pexe37/icons.py
pexe37/mf3.py
pexe37/mf34.py
pexe37/patch_distutils.py
pexe37/pexe37_distutils.py
pexe37/resources.dll
pexe37/resources.py
pexe37/run-py3.7-win-amd64.exe
pexe37/run_ctypes_dll-py3.7-win-amd64.dll
pexe37/run_w-py3.7-win-amd64.exe
pexe37/runtime.py
pexe37/setup_template.py
pexe37/versioninfo.py
pexe37-0.9.6.5.dist-info/LICENSE.txt
pexe37-0.9.6.5.dist-info/METADATA
pexe37-0.9.6.5.dist-info/WHEEL
pexe37-0.9.6.5.dist-info/entry_points.txt
pexe37-0.9.6.5.dist-info/top_level.txt
pexe37-0.9.6.5.dist-info/RECORD
